micropython_hts221/__init__.py
micropython_hts221/hts221.py
micropython_hts221/i2c_helpers.py
micropython_hts221-0.1.0.dist-info/LICENSE
micropython_hts221-0.1.0.dist-info/METADATA
micropython_hts221-0.1.0.dist-info/WHEEL
micropython_hts221-0.1.0.dist-info/top_level.txt
micropython_hts221-0.1.0.dist-info/RECORD
