Metadata-Version: 2.1
Name: micropython-hts221
Version: 0.1.0
Summary: MicroPython Driver for the HTS221 Humidity Sensor
Author-email: JDM <xxyx@mailmeto.mozmail.com>
License: MIT
Project-URL: Homepage, https://github.com/jposada202020/MicroPython_HTS221
Keywords: sensor,micropython,hts221,humidity,sensor,micropython,driver,hts221
Classifier: Intended Audience :: Developers
Classifier: Topic :: Software Development :: Libraries
Classifier: Topic :: Software Development :: Embedded Systems
Classifier: Topic :: System :: Hardware
Classifier: License :: OSI Approved :: MIT License
Classifier: Programming Language :: Python :: Implementation :: MicroPython
License-File: LICENSE
